ecstools/__init__.py
ecstools/main.py
ecstools/commands/__init__.py
ecstools/commands/cluster/__init__.py
ecstools/commands/cluster/ls.py
ecstools/commands/service/__init__.py
ecstools/commands/service/deploy.py
ecstools/commands/service/desc.py
ecstools/commands/service/env.py
ecstools/commands/service/exec.py
ecstools/commands/service/ls.py
ecstools/commands/service/scale.py
ecstools/commands/service/top.py
ecstools/commands/task-definition/__init__.py
ecstools/commands/task-definition/ls.py
ecstools/lib/__init__.py
ecstools/lib/cli.py
ecstools/lib/config.py
ecstools/lib/utils.py
ecstools/resources/__init__.py
ecstools/resources/ecr.py
ecstools/resources/service.py
ecstools/resources/task_definition.py
ecstools/tests/__init__.py
ecstools/tests/conftest.py
ecstools/tests/test_main.py
ecstools/tests/commands/__init__.py
ecstools/tests/commands/test_cluster.py
ecstools/tests/commands/test_service.py
ecstools/tests/commands/test_task_definition.py
ecstools-0.2.7.dist-info/LICENSE
ecstools-0.2.7.dist-info/METADATA
ecstools-0.2.7.dist-info/WHEEL
ecstools-0.2.7.dist-info/entry_points.txt
ecstools-0.2.7.dist-info/top_level.txt
ecstools-0.2.7.dist-info/RECORD
