Metadata-Version: 2.1
Name: ecstools
Version: 0.2.7
Summary: Utilities for AWS ECS
Home-page: https://github.com/boroivanov/ecs-tools
Author: Borislav Ivanov
Author-email: borogl@gmail.com
License: MIT license
Classifier: Programming Language :: Python
Classifier: Programming Language :: Python :: 3
Classifier: Programming Language :: Python :: 3.3
Classifier: Programming Language :: Python :: 3.4
Classifier: Programming Language :: Python :: 3.5
Classifier: Programming Language :: Python :: 3.6
Classifier: Programming Language :: Python :: 3.7
Classifier: Programming Language :: Python :: 3.8
Classifier: Programming Language :: Python :: 3.9
License-File: LICENSE
Requires-Dist: Click (>=6.0)
Requires-Dist: boto3 (>=1.5.33)
Requires-Dist: reprint (>=0.5.1)
Requires-Dist: configparser (>=3.5.0)
